yowasp_nextpnr_himbaechel_gowin/__init__.py
yowasp_nextpnr_himbaechel_gowin/nextpnr-himbaechel-gowin.wasm
yowasp_nextpnr_himbaechel_gowin/share/himbaechel/gowin/chipdb-GW1N-1.bin
yowasp_nextpnr_himbaechel_gowin/share/himbaechel/gowin/chipdb-GW1N-4.bin
yowasp_nextpnr_himbaechel_gowin/share/himbaechel/gowin/chipdb-GW1N-9.bin
yowasp_nextpnr_himbaechel_gowin/share/himbaechel/gowin/chipdb-GW1N-9C.bin
yowasp_nextpnr_himbaechel_gowin/share/himbaechel/gowin/chipdb-GW1NS-4.bin
yowasp_nextpnr_himbaechel_gowin/share/himbaechel/gowin/chipdb-GW1NZ-1.bin
yowasp_nextpnr_himbaechel_gowin/share/himbaechel/gowin/chipdb-GW2A-18.bin
yowasp_nextpnr_himbaechel_gowin/share/himbaechel/gowin/chipdb-GW2A-18C.bin
yowasp_nextpnr_himbaechel_gowin/share/himbaechel/gowin/chipdb-GW5A-25A.bin
yowasp_nextpnr_himbaechel_gowin-0.9.0.0.post686.dist-info/METADATA
yowasp_nextpnr_himbaechel_gowin-0.9.0.0.post686.dist-info/WHEEL
yowasp_nextpnr_himbaechel_gowin-0.9.0.0.post686.dist-info/entry_points.txt
yowasp_nextpnr_himbaechel_gowin-0.9.0.0.post686.dist-info/top_level.txt
yowasp_nextpnr_himbaechel_gowin-0.9.0.0.post686.dist-info/RECORD
