Metadata-Version: 2.4
Name: yowasp-nextpnr-himbaechel-gowin
Version: 0.9.0.0.post686
Summary: nextpnr-himbaechel-gowin FPGA place and route tool
Author-email: Catherine <whitequark@whitequark.org>
License-Expression: ISC
Project-URL: Homepage, https://yowasp.org/
Project-URL: Source Code, https://github.com/YoWASP/nextpnr
Project-URL: Bug Tracker, https://github.com/YoWASP/nextpnr/issues
Requires-Dist: yowasp-runtime~=1.1
Requires-Dist: Apycula==0.25
